<odoo>
    <record id="view_hr_payslip_tree_inherit_lines" model="ir.ui.view">
    <field name="name">hr.payslip.tree.inherit.lines</field>
    <field name="model">hr.payslip</field>
    <field name="inherit_id" ref="hr_payroll.view_hr_payslip_tree"/>
    <field name="arch" type="xml">
        <xpath expr="//field[@name='gross_wage']" position="after">
            <field name="line_basic"/>
            <field name="line_db"/>
            <field name="line_mob"/>
            <field name="line_qvelmoqmedeba"/>
            <field name="line_gross"/>
            <field name="line_fitpass"/>
            <field name="line_sap"/>
            <field name="line_sapcomp"/>
            <field name="line_income"/>
            <field name="line_profkavsh"/>
            <field name="line_profkavsh_1"/>
            <field name="line_fondi"/>
            <field name="line_net"/>
            <field name="line_biulet"/>
            <field name="line_agsr"/>
            <field name="line_compdazg"/>
            <field name="line_avansi"/>
<!--            <field name="line_compdazg"/>-->
            </xpath>
    </field>
    </record>
</odoo>
